pyspeak_command-3.1.1.dist-info/licenses/LICENSE
speak_command/__init__.py
speak_command/controller.py
speak_command/main.py
speak_command/utils.py
pyspeak_command-3.1.1.dist-info/METADATA
pyspeak_command-3.1.1.dist-info/WHEEL
pyspeak_command-3.1.1.dist-info/entry_points.txt
pyspeak_command-3.1.1.dist-info/top_level.txt
pyspeak_command-3.1.1.dist-info/RECORD
