Metadata-Version: 2.4
Name: pyspeak_command
Version: 3.1.1
Summary: Um utilitário para ler em voz alta e/ou traduzir comandos do terminal, scripts Python, e arquivos de texto
Home-page: https://github.com/higormcarnauba/speak_command
Author: Cícero Higor
Author-email: higormc2015@gmail.com
Classifier: Programming Language :: Python :: 3
Classifier: License :: OSI Approved :: MIT License
Classifier: Operating System :: OS Independent
Requires-Python: >=3.7
License-File: LICENSE
Requires-Dist: pyttsx3
Requires-Dist: pynput
Requires-Dist: deep_translator
Requires-Dist: ftfy
Dynamic: author
Dynamic: author-email
Dynamic: classifier
Dynamic: description
Dynamic: description-content-type
Dynamic: home-page
Dynamic: license-file
Dynamic: requires-dist
Dynamic: requires-python
Dynamic: summary
